{
    "player_alias": "tabrao",
    "matchs_count": 768,
    "start_date": "2022-11-04",
    "end_date": "2023-07-02",
    "pings_mean": 14.941,
    "pings_constancy": 0.737,
    "pings_most_frequency": [
        10,
        4,
        11,
        6,
        7
    ],
    "pings_ratio": 0.548,
    "pings_median": 13.0,
    "pings_sum": "11475",
    "pings_std": 10.209,
    "win_pings_count": "404",
    "win_pings_mean": 16.171,
    "win_pings_median": 15.0,
    "win_pings_sum": "6533",
    "win_pings_std": 10.405,
    "win_pings_ratio_mean": 0.602,
    "win_pings_ratio_std": 0.348,
    "lose_pings_count": "364",
    "lose_pings_mean": 13.577,
    "lose_pings_median": 11.0,
    "lose_pings_sum": "4942",
    "lose_pings_std": 9.823,
    "lose_pings_ratio_mean": 0.488,
    "lose_pings_ratio_std": 0.315
}