{
    "player_alias": "robo",
    "matchs_count": 523,
    "start_date": "2022-11-02",
    "end_date": "2023-06-29",
    "pings_mean": 18.474,
    "pings_constancy": 0.683,
    "pings_ratio": 0.71,
    "pings_median": 17.0,
    "pings_sum": "9662",
    "pings_std": 10.378,
    "win_pings_count": "280",
    "win_pings_mean": 16.929,
    "win_pings_median": 16.0,
    "win_pings_sum": "4740",
    "win_pings_std": 9.107,
    "win_pings_ratio_mean": 0.672,
    "win_pings_ratio_std": 0.318,
    "lose_pings_count": "243",
    "lose_pings_mean": 20.255,
    "lose_pings_median": 19.0,
    "lose_pings_sum": "4922",
    "lose_pings_std": 11.434,
    "lose_pings_ratio_mean": 0.754,
    "lose_pings_ratio_std": 0.367
}